Netaxstimrie/__init__.py
Netaxstimrie/netnetwork.cpython-311-darwin.so
Netaxstimrie-0.1.1.dist-info/LICENSE.txt
Netaxstimrie-0.1.1.dist-info/METADATA
Netaxstimrie-0.1.1.dist-info/WHEEL
Netaxstimrie-0.1.1.dist-info/top_level.txt
Netaxstimrie-0.1.1.dist-info/RECORD
